watttime_client/__init__.py
watttime_client/client.py
watttime_client-0.2.dist-info/DESCRIPTION.rst
watttime_client-0.2.dist-info/METADATA
watttime_client-0.2.dist-info/metadata.json
watttime_client-0.2.dist-info/RECORD
watttime_client-0.2.dist-info/top_level.txt
watttime_client-0.2.dist-info/WHEEL
