Metadata-Version: 2.0
Name: watttime-client
Version: 0.2
Summary: Python client library for the WattTime API
Home-page: https://github.com/WattTime/watttime-python-client
Author: WattTime
Author-email: dev@WattTime.org
License: Apache
Platform: UNKNOWN
Classifier: Development Status :: 3 - Alpha
Classifier: Environment :: Web Environment
Classifier: Intended Audience :: Developers
Classifier: License :: OSI Approved :: Apache Software License
Classifier: Operating System :: OS Independent
Classifier: Natural Language :: English
Classifier: Programming Language :: Python :: 2
Classifier: Programming Language :: Python :: 2.7
Classifier: Topic :: Internet :: WWW/HTTP
